sptranslator/__init__.py
sptranslator/translator.py
SPTranslator-0.0.2.dist-info/LICENSE
SPTranslator-0.0.2.dist-info/METADATA
SPTranslator-0.0.2.dist-info/WHEEL
SPTranslator-0.0.2.dist-info/top_level.txt
SPTranslator-0.0.2.dist-info/RECORD
