Metadata-Version: 2.1
Name: SPTranslator
Version: 0.0.2
Summary: Python library for translating in-code comments and documentation while preserving syntax and structure.
Author-email: Yuta Oriike <nontrivial@hotmail.co.jp>
Project-URL: Homepage, https://github.com/uta0x89/SPTranslator
Classifier: Programming Language :: Python :: 3
Classifier: License :: OSI Approved :: MIT License
Classifier: Operating System :: OS Independent
Requires-Python: >=3.6
License-File: LICENSE
Requires-Dist: openai
Requires-Dist: tiktoken
Requires-Dist: lark
Provides-Extra: dev
Requires-Dist: pytest ; extra == 'dev'
